<annotation>
	<folder>VOC1</folder>
	<filename>0_3282.jpg</filename>
	<size>
		<width>256</width>
		<height>256</height>
		<depth>3</depth>
	</size>
	<segmented>0</segmented>
	<object>
		<name>296</name>
		<pose>Unspecified</pose>
		<truncated>0</truncated>
		<difficult>0</difficult>
		<bndbox>
			<xmin>21.0</xmin>
			<ymin>42.0</ymin>
			<xmax>92.0</xmax>
			<ymax>113.0</ymax>
		</bndbox>
	</object>
	<object>
		<name>378</name>
		<pose>Unspecified</pose>
		<truncated>0</truncated>
		<difficult>0</difficult>
		<bndbox>
			<xmin>167.0</xmin>
			<ymin>2.0</ymin>
			<xmax>245.0</xmax>
			<ymax>80.0</ymax>
		</bndbox>
	</object>
	<object>
		<name>968</name>
		<pose>Unspecified</pose>
		<truncated>0</truncated>
		<difficult>0</difficult>
		<bndbox>
			<xmin>59.0</xmin>
			<ymin>154.0</ymin>
			<xmax>138.0</xmax>
			<ymax>233.0</ymax>
		</bndbox>
	</object>
	<object>
		<name>633</name>
		<pose>Unspecified</pose>
		<truncated>0</truncated>
		<difficult>0</difficult>
		<bndbox>
			<xmin>163.0</xmin>
			<ymin>178.0</ymin>
			<xmax>239.0</xmax>
			<ymax>254.0</ymax>
		</bndbox>
	</object>
	<object>
		<name>760</name>
		<pose>Unspecified</pose>
		<truncated>0</truncated>
		<difficult>0</difficult>
		<bndbox>
			<xmin>141.0</xmin>
			<ymin>87.0</ymin>
			<xmax>221.0</xmax>
			<ymax>167.0</ymax>
		</bndbox>
	</object>
	<object>
		<name>600</name>
		<pose>Unspecified</pose>
		<truncated>0</truncated>
		<difficult>0</difficult>
		<bndbox>
			<xmin>91.0</xmin>
			<ymin>28.0</ymin>
			<xmax>142.0</xmax>
			<ymax>79.0</ymax>
		</bndbox>
	</object>
</annotation>