<annotation>
	<folder>VOC1</folder>
	<filename>0_349.jpg</filename>
	<size>
		<width>256</width>
		<height>256</height>
		<depth>3</depth>
	</size>
	<segmented>0</segmented>
	<object>
		<name>409</name>
		<pose>Unspecified</pose>
		<truncated>0</truncated>
		<difficult>0</difficult>
		<bndbox>
			<xmin>24.0</xmin>
			<ymin>24.0</ymin>
			<xmax>98.0</xmax>
			<ymax>98.0</ymax>
		</bndbox>
	</object>
	<object>
		<name>2</name>
		<pose>Unspecified</pose>
		<truncated>0</truncated>
		<difficult>0</difficult>
		<bndbox>
			<xmin>128.0</xmin>
			<ymin>119.0</ymin>
			<xmax>192.0</xmax>
			<ymax>183.0</ymax>
		</bndbox>
	</object>
	<object>
		<name>626</name>
		<pose>Unspecified</pose>
		<truncated>0</truncated>
		<difficult>0</difficult>
		<bndbox>
			<xmin>0.0</xmin>
			<ymin>129.0</ymin>
			<xmax>64.0</xmax>
			<ymax>193.0</ymax>
		</bndbox>
	</object>
	<object>
		<name>219</name>
		<pose>Unspecified</pose>
		<truncated>0</truncated>
		<difficult>0</difficult>
		<bndbox>
			<xmin>65.0</xmin>
			<ymin>139.0</ymin>
			<xmax>139.0</xmax>
			<ymax>213.0</ymax>
		</bndbox>
	</object>
	<object>
		<name>829</name>
		<pose>Unspecified</pose>
		<truncated>0</truncated>
		<difficult>0</difficult>
		<bndbox>
			<xmin>180.0</xmin>
			<ymin>72.0</ymin>
			<xmax>256.0</xmax>
			<ymax>148.0</ymax>
		</bndbox>
	</object>
	<object>
		<name>500</name>
		<pose>Unspecified</pose>
		<truncated>0</truncated>
		<difficult>0</difficult>
		<bndbox>
			<xmin>128.0</xmin>
			<ymin>5.0</ymin>
			<xmax>199.0</xmax>
			<ymax>76.0</ymax>
		</bndbox>
	</object>
</annotation>