<annotation>
	<folder>VOC1</folder>
	<filename>0_366.jpg</filename>
	<size>
		<width>256</width>
		<height>256</height>
		<depth>3</depth>
	</size>
	<segmented>0</segmented>
	<object>
		<name>551</name>
		<pose>Unspecified</pose>
		<truncated>0</truncated>
		<difficult>0</difficult>
		<bndbox>
			<xmin>43.0</xmin>
			<ymin>51.0</ymin>
			<xmax>108.0</xmax>
			<ymax>121.0</ymax>
		</bndbox>
	</object>
	<object>
		<name>579</name>
		<pose>Unspecified</pose>
		<truncated>0</truncated>
		<difficult>0</difficult>
		<bndbox>
			<xmin>112.0</xmin>
			<ymin>97.0</ymin>
			<xmax>177.0</xmax>
			<ymax>167.0</ymax>
		</bndbox>
	</object>
	<object>
		<name>286</name>
		<pose>Unspecified</pose>
		<truncated>0</truncated>
		<difficult>0</difficult>
		<bndbox>
			<xmin>31.0</xmin>
			<ymin>157.0</ymin>
			<xmax>89.0</xmax>
			<ymax>220.0</ymax>
		</bndbox>
	</object>
	<object>
		<name>462</name>
		<pose>Unspecified</pose>
		<truncated>0</truncated>
		<difficult>0</difficult>
		<bndbox>
			<xmin>110.0</xmin>
			<ymin>174.0</ymin>
			<xmax>180.0</xmax>
			<ymax>249.0</ymax>
		</bndbox>
	</object>
	<object>
		<name>242</name>
		<pose>Unspecified</pose>
		<truncated>0</truncated>
		<difficult>0</difficult>
		<bndbox>
			<xmin>150.0</xmin>
			<ymin>26.0</ymin>
			<xmax>221.0</xmax>
			<ymax>102.0</ymax>
		</bndbox>
	</object>
</annotation>