<annotation>
	<folder>VOC1</folder>
	<filename>0_426.jpg</filename>
	<size>
		<width>256</width>
		<height>256</height>
		<depth>3</depth>
	</size>
	<segmented>0</segmented>
	<object>
		<name>720</name>
		<pose>Unspecified</pose>
		<truncated>0</truncated>
		<difficult>0</difficult>
		<bndbox>
			<xmin>11.0</xmin>
			<ymin>53.0</ymin>
			<xmax>88.0</xmax>
			<ymax>130.0</ymax>
		</bndbox>
	</object>
	<object>
		<name>620</name>
		<pose>Unspecified</pose>
		<truncated>0</truncated>
		<difficult>0</difficult>
		<bndbox>
			<xmin>170.0</xmin>
			<ymin>107.0</ymin>
			<xmax>240.0</xmax>
			<ymax>177.0</ymax>
		</bndbox>
	</object>
	<object>
		<name>952</name>
		<pose>Unspecified</pose>
		<truncated>0</truncated>
		<difficult>0</difficult>
		<bndbox>
			<xmin>83.0</xmin>
			<ymin>60.0</ymin>
			<xmax>155.0</xmax>
			<ymax>132.0</ymax>
		</bndbox>
	</object>
	<object>
		<name>301</name>
		<pose>Unspecified</pose>
		<truncated>0</truncated>
		<difficult>0</difficult>
		<bndbox>
			<xmin>82.0</xmin>
			<ymin>142.0</ymin>
			<xmax>153.0</xmax>
			<ymax>213.0</ymax>
		</bndbox>
	</object>
	<object>
		<name>24</name>
		<pose>Unspecified</pose>
		<truncated>0</truncated>
		<difficult>0</difficult>
		<bndbox>
			<xmin>178.0</xmin>
			<ymin>33.0</ymin>
			<xmax>245.0</xmax>
			<ymax>100.0</ymax>
		</bndbox>
	</object>
	<object>
		<name>272</name>
		<pose>Unspecified</pose>
		<truncated>0</truncated>
		<difficult>0</difficult>
		<bndbox>
			<xmin>25.0</xmin>
			<ymin>118.0</ymin>
			<xmax>79.0</xmax>
			<ymax>172.0</ymax>
		</bndbox>
	</object>
</annotation>