<annotation>
	<folder>VOC1</folder>
	<filename>0_5069.jpg</filename>
	<size>
		<width>256</width>
		<height>256</height>
		<depth>3</depth>
	</size>
	<segmented>0</segmented>
	<object>
		<name>511</name>
		<pose>Unspecified</pose>
		<truncated>0</truncated>
		<difficult>0</difficult>
		<bndbox>
			<xmin>49.0</xmin>
			<ymin>17.0</ymin>
			<xmax>122.0</xmax>
			<ymax>90.0</ymax>
		</bndbox>
	</object>
	<object>
		<name>474</name>
		<pose>Unspecified</pose>
		<truncated>0</truncated>
		<difficult>0</difficult>
		<bndbox>
			<xmin>165.0</xmin>
			<ymin>77.0</ymin>
			<xmax>234.0</xmax>
			<ymax>146.0</ymax>
		</bndbox>
	</object>
	<object>
		<name>409</name>
		<pose>Unspecified</pose>
		<truncated>0</truncated>
		<difficult>0</difficult>
		<bndbox>
			<xmin>88.0</xmin>
			<ymin>120.0</ymin>
			<xmax>168.0</xmax>
			<ymax>200.0</ymax>
		</bndbox>
	</object>
	<object>
		<name>684</name>
		<pose>Unspecified</pose>
		<truncated>0</truncated>
		<difficult>0</difficult>
		<bndbox>
			<xmin>49.0</xmin>
			<ymin>174.0</ymin>
			<xmax>128.0</xmax>
			<ymax>253.0</ymax>
		</bndbox>
	</object>
	<object>
		<name>979</name>
		<pose>Unspecified</pose>
		<truncated>0</truncated>
		<difficult>0</difficult>
		<bndbox>
			<xmin>185.0</xmin>
			<ymin>7.0</ymin>
			<xmax>247.0</xmax>
			<ymax>69.0</ymax>
		</bndbox>
	</object>
	<object>
		<name>251</name>
		<pose>Unspecified</pose>
		<truncated>0</truncated>
		<difficult>0</difficult>
		<bndbox>
			<xmin>11.0</xmin>
			<ymin>71.0</ymin>
			<xmax>70.0</xmax>
			<ymax>130.0</ymax>
		</bndbox>
	</object>
</annotation>