<annotation>
	<folder>VOC1</folder>
	<filename>0_5840.jpg</filename>
	<size>
		<width>256</width>
		<height>256</height>
		<depth>3</depth>
	</size>
	<segmented>0</segmented>
	<object>
		<name>196</name>
		<pose>Unspecified</pose>
		<truncated>0</truncated>
		<difficult>0</difficult>
		<bndbox>
			<xmin>21.0</xmin>
			<ymin>48.0</ymin>
			<xmax>95.0</xmax>
			<ymax>127.0</ymax>
		</bndbox>
	</object>
	<object>
		<name>332</name>
		<pose>Unspecified</pose>
		<truncated>0</truncated>
		<difficult>0</difficult>
		<bndbox>
			<xmin>16.0</xmin>
			<ymin>141.0</ymin>
			<xmax>86.0</xmax>
			<ymax>216.0</ymax>
		</bndbox>
	</object>
	<object>
		<name>55</name>
		<pose>Unspecified</pose>
		<truncated>0</truncated>
		<difficult>0</difficult>
		<bndbox>
			<xmin>72.0</xmin>
			<ymin>179.0</ymin>
			<xmax>129.0</xmax>
			<ymax>241.0</ymax>
		</bndbox>
	</object>
	<object>
		<name>175</name>
		<pose>Unspecified</pose>
		<truncated>0</truncated>
		<difficult>0</difficult>
		<bndbox>
			<xmin>139.0</xmin>
			<ymin>136.0</ymin>
			<xmax>210.0</xmax>
			<ymax>212.0</ymax>
		</bndbox>
	</object>
	<object>
		<name>486</name>
		<pose>Unspecified</pose>
		<truncated>0</truncated>
		<difficult>0</difficult>
		<bndbox>
			<xmin>109.0</xmin>
			<ymin>30.0</ymin>
			<xmax>163.0</xmax>
			<ymax>89.0</ymax>
		</bndbox>
	</object>
</annotation>