<annotation>
	<folder>VOC1</folder>
	<filename>0_8129.jpg</filename>
	<size>
		<width>256</width>
		<height>256</height>
		<depth>3</depth>
	</size>
	<segmented>0</segmented>
	<object>
		<name>494</name>
		<pose>Unspecified</pose>
		<truncated>0</truncated>
		<difficult>0</difficult>
		<bndbox>
			<xmin>35.0</xmin>
			<ymin>35.0</ymin>
			<xmax>113.0</xmax>
			<ymax>113.0</ymax>
		</bndbox>
	</object>
	<object>
		<name>677</name>
		<pose>Unspecified</pose>
		<truncated>0</truncated>
		<difficult>0</difficult>
		<bndbox>
			<xmin>170.0</xmin>
			<ymin>171.0</ymin>
			<xmax>247.0</xmax>
			<ymax>248.0</ymax>
		</bndbox>
	</object>
	<object>
		<name>309</name>
		<pose>Unspecified</pose>
		<truncated>0</truncated>
		<difficult>0</difficult>
		<bndbox>
			<xmin>72.0</xmin>
			<ymin>146.0</ymin>
			<xmax>148.0</xmax>
			<ymax>222.0</ymax>
		</bndbox>
	</object>
	<object>
		<name>326</name>
		<pose>Unspecified</pose>
		<truncated>0</truncated>
		<difficult>0</difficult>
		<bndbox>
			<xmin>132.0</xmin>
			<ymin>114.0</ymin>
			<xmax>215.0</xmax>
			<ymax>197.0</ymax>
		</bndbox>
	</object>
	<object>
		<name>871</name>
		<pose>Unspecified</pose>
		<truncated>0</truncated>
		<difficult>0</difficult>
		<bndbox>
			<xmin>164.0</xmin>
			<ymin>16.0</ymin>
			<xmax>248.0</xmax>
			<ymax>100.0</ymax>
		</bndbox>
	</object>
	<object>
		<name>267</name>
		<pose>Unspecified</pose>
		<truncated>0</truncated>
		<difficult>0</difficult>
		<bndbox>
			<xmin>5.0</xmin>
			<ymin>145.0</ymin>
			<xmax>86.0</xmax>
			<ymax>226.0</ymax>
		</bndbox>
	</object>
</annotation>