<annotation>
	<folder>VOC1</folder>
	<filename>0_8254.jpg</filename>
	<size>
		<width>256</width>
		<height>256</height>
		<depth>3</depth>
	</size>
	<segmented>0</segmented>
	<object>
		<name>69</name>
		<pose>Unspecified</pose>
		<truncated>0</truncated>
		<difficult>0</difficult>
		<bndbox>
			<xmin>12.0</xmin>
			<ymin>7.0</ymin>
			<xmax>86.0</xmax>
			<ymax>81.0</ymax>
		</bndbox>
	</object>
	<object>
		<name>559</name>
		<pose>Unspecified</pose>
		<truncated>0</truncated>
		<difficult>0</difficult>
		<bndbox>
			<xmin>73.0</xmin>
			<ymin>130.0</ymin>
			<xmax>149.0</xmax>
			<ymax>206.0</ymax>
		</bndbox>
	</object>
	<object>
		<name>909</name>
		<pose>Unspecified</pose>
		<truncated>0</truncated>
		<difficult>0</difficult>
		<bndbox>
			<xmin>147.0</xmin>
			<ymin>111.0</ymin>
			<xmax>215.0</xmax>
			<ymax>179.0</ymax>
		</bndbox>
	</object>
	<object>
		<name>965</name>
		<pose>Unspecified</pose>
		<truncated>0</truncated>
		<difficult>0</difficult>
		<bndbox>
			<xmin>118.0</xmin>
			<ymin>29.0</ymin>
			<xmax>177.0</xmax>
			<ymax>88.0</ymax>
		</bndbox>
	</object>
	<object>
		<name>907</name>
		<pose>Unspecified</pose>
		<truncated>0</truncated>
		<difficult>0</difficult>
		<bndbox>
			<xmin>188.0</xmin>
			<ymin>35.0</ymin>
			<xmax>256.0</xmax>
			<ymax>103.0</ymax>
		</bndbox>
	</object>
	<object>
		<name>360</name>
		<pose>Unspecified</pose>
		<truncated>0</truncated>
		<difficult>0</difficult>
		<bndbox>
			<xmin>53.0</xmin>
			<ymin>48.0</ymin>
			<xmax>127.0</xmax>
			<ymax>122.0</ymax>
		</bndbox>
	</object>
</annotation>