<annotation>
	<folder>VOC1</folder>
	<filename>0_858.jpg</filename>
	<size>
		<width>256</width>
		<height>256</height>
		<depth>3</depth>
	</size>
	<segmented>0</segmented>
	<object>
		<name>76</name>
		<pose>Unspecified</pose>
		<truncated>0</truncated>
		<difficult>0</difficult>
		<bndbox>
			<xmin>40.0</xmin>
			<ymin>30.0</ymin>
			<xmax>112.0</xmax>
			<ymax>107.0</ymax>
		</bndbox>
	</object>
	<object>
		<name>729</name>
		<pose>Unspecified</pose>
		<truncated>0</truncated>
		<difficult>0</difficult>
		<bndbox>
			<xmin>16.0</xmin>
			<ymin>163.0</ymin>
			<xmax>91.0</xmax>
			<ymax>243.0</ymax>
		</bndbox>
	</object>
	<object>
		<name>113</name>
		<pose>Unspecified</pose>
		<truncated>0</truncated>
		<difficult>0</difficult>
		<bndbox>
			<xmin>105.0</xmin>
			<ymin>77.0</ymin>
			<xmax>180.0</xmax>
			<ymax>157.0</ymax>
		</bndbox>
	</object>
	<object>
		<name>433</name>
		<pose>Unspecified</pose>
		<truncated>0</truncated>
		<difficult>0</difficult>
		<bndbox>
			<xmin>163.0</xmin>
			<ymin>136.0</ymin>
			<xmax>217.0</xmax>
			<ymax>195.0</ymax>
		</bndbox>
	</object>
	<object>
		<name>165</name>
		<pose>Unspecified</pose>
		<truncated>0</truncated>
		<difficult>0</difficult>
		<bndbox>
			<xmin>13.0</xmin>
			<ymin>97.0</ymin>
			<xmax>87.0</xmax>
			<ymax>176.0</ymax>
		</bndbox>
	</object>
	<object>
		<name>859</name>
		<pose>Unspecified</pose>
		<truncated>0</truncated>
		<difficult>0</difficult>
		<bndbox>
			<xmin>87.0</xmin>
			<ymin>147.0</ymin>
			<xmax>160.0</xmax>
			<ymax>225.0</ymax>
		</bndbox>
	</object>
</annotation>