<annotation>
	<folder>VOC1</folder>
	<filename>0_1134.jpg</filename>
	<size>
		<width>256</width>
		<height>256</height>
		<depth>3</depth>
	</size>
	<segmented>0</segmented>
	<object>
		<name>679</name>
		<pose>Unspecified</pose>
		<truncated>0</truncated>
		<difficult>0</difficult>
		<bndbox>
			<xmin>2.0</xmin>
			<ymin>19.0</ymin>
			<xmax>86.0</xmax>
			<ymax>103.0</ymax>
		</bndbox>
	</object>
	<object>
		<name>723</name>
		<pose>Unspecified</pose>
		<truncated>0</truncated>
		<difficult>0</difficult>
		<bndbox>
			<xmin>166.0</xmin>
			<ymin>125.0</ymin>
			<xmax>256.0</xmax>
			<ymax>215.0</ymax>
		</bndbox>
	</object>
	<object>
		<name>768</name>
		<pose>Unspecified</pose>
		<truncated>0</truncated>
		<difficult>0</difficult>
		<bndbox>
			<xmin>25.0</xmin>
			<ymin>143.0</ymin>
			<xmax>101.0</xmax>
			<ymax>219.0</ymax>
		</bndbox>
	</object>
	<object>
		<name>900</name>
		<pose>Unspecified</pose>
		<truncated>0</truncated>
		<difficult>0</difficult>
		<bndbox>
			<xmin>107.0</xmin>
			<ymin>45.0</ymin>
			<xmax>195.0</xmax>
			<ymax>133.0</ymax>
		</bndbox>
	</object>
</annotation>