<annotation>
	<folder>VOC1</folder>
	<filename>0_3791.jpg</filename>
	<size>
		<width>256</width>
		<height>256</height>
		<depth>3</depth>
	</size>
	<segmented>0</segmented>
	<object>
		<name>353</name>
		<pose>Unspecified</pose>
		<truncated>0</truncated>
		<difficult>0</difficult>
		<bndbox>
			<xmin>9.0</xmin>
			<ymin>32.0</ymin>
			<xmax>93.0</xmax>
			<ymax>116.0</ymax>
		</bndbox>
	</object>
	<object>
		<name>418</name>
		<pose>Unspecified</pose>
		<truncated>0</truncated>
		<difficult>0</difficult>
		<bndbox>
			<xmin>108.0</xmin>
			<ymin>159.0</ymin>
			<xmax>194.0</xmax>
			<ymax>245.0</ymax>
		</bndbox>
	</object>
	<object>
		<name>696</name>
		<pose>Unspecified</pose>
		<truncated>0</truncated>
		<difficult>0</difficult>
		<bndbox>
			<xmin>122.0</xmin>
			<ymin>78.0</ymin>
			<xmax>195.0</xmax>
			<ymax>151.0</ymax>
		</bndbox>
	</object>
	<object>
		<name>457</name>
		<pose>Unspecified</pose>
		<truncated>0</truncated>
		<difficult>0</difficult>
		<bndbox>
			<xmin>21.0</xmin>
			<ymin>158.0</ymin>
			<xmax>115.0</xmax>
			<ymax>252.0</ymax>
		</bndbox>
	</object>
</annotation>