<annotation>
	<folder>VOC1</folder>
	<filename>0_4150.jpg</filename>
	<size>
		<width>256</width>
		<height>256</height>
		<depth>3</depth>
	</size>
	<segmented>0</segmented>
	<object>
		<name>850</name>
		<pose>Unspecified</pose>
		<truncated>0</truncated>
		<difficult>0</difficult>
		<bndbox>
			<xmin>16.0</xmin>
			<ymin>30.0</ymin>
			<xmax>79.0</xmax>
			<ymax>98.0</ymax>
		</bndbox>
	</object>
	<object>
		<name>445</name>
		<pose>Unspecified</pose>
		<truncated>0</truncated>
		<difficult>0</difficult>
		<bndbox>
			<xmin>109.0</xmin>
			<ymin>154.0</ymin>
			<xmax>183.0</xmax>
			<ymax>233.0</ymax>
		</bndbox>
	</object>
	<object>
		<name>228</name>
		<pose>Unspecified</pose>
		<truncated>0</truncated>
		<difficult>0</difficult>
		<bndbox>
			<xmin>84.0</xmin>
			<ymin>70.0</ymin>
			<xmax>170.0</xmax>
			<ymax>161.0</ymax>
		</bndbox>
	</object>
	<object>
		<name>192</name>
		<pose>Unspecified</pose>
		<truncated>0</truncated>
		<difficult>0</difficult>
		<bndbox>
			<xmin>15.0</xmin>
			<ymin>112.0</ymin>
			<xmax>101.0</xmax>
			<ymax>203.0</ymax>
		</bndbox>
	</object>
	<object>
		<name>465</name>
		<pose>Unspecified</pose>
		<truncated>0</truncated>
		<difficult>0</difficult>
		<bndbox>
			<xmin>159.0</xmin>
			<ymin>42.0</ymin>
			<xmax>225.0</xmax>
			<ymax>113.0</ymax>
		</bndbox>
	</object>
</annotation>