<annotation>
	<folder>VOC1</folder>
	<filename>0_4612.jpg</filename>
	<size>
		<width>256</width>
		<height>256</height>
		<depth>3</depth>
	</size>
	<segmented>0</segmented>
	<object>
		<name>317</name>
		<pose>Unspecified</pose>
		<truncated>0</truncated>
		<difficult>0</difficult>
		<bndbox>
			<xmin>6.0</xmin>
			<ymin>2.0</ymin>
			<xmax>84.0</xmax>
			<ymax>80.0</ymax>
		</bndbox>
	</object>
	<object>
		<name>206</name>
		<pose>Unspecified</pose>
		<truncated>0</truncated>
		<difficult>0</difficult>
		<bndbox>
			<xmin>95.0</xmin>
			<ymin>66.0</ymin>
			<xmax>188.0</xmax>
			<ymax>159.0</ymax>
		</bndbox>
	</object>
	<object>
		<name>773</name>
		<pose>Unspecified</pose>
		<truncated>0</truncated>
		<difficult>0</difficult>
		<bndbox>
			<xmin>138.0</xmin>
			<ymin>157.0</ymin>
			<xmax>232.0</xmax>
			<ymax>251.0</ymax>
		</bndbox>
	</object>
	<object>
		<name>99</name>
		<pose>Unspecified</pose>
		<truncated>0</truncated>
		<difficult>0</difficult>
		<bndbox>
			<xmin>51.0</xmin>
			<ymin>168.0</ymin>
			<xmax>136.0</xmax>
			<ymax>253.0</ymax>
		</bndbox>
	</object>
	<object>
		<name>242</name>
		<pose>Unspecified</pose>
		<truncated>0</truncated>
		<difficult>0</difficult>
		<bndbox>
			<xmin>149.0</xmin>
			<ymin>3.0</ymin>
			<xmax>238.0</xmax>
			<ymax>92.0</ymax>
		</bndbox>
	</object>
	<object>
		<name>688</name>
		<pose>Unspecified</pose>
		<truncated>0</truncated>
		<difficult>0</difficult>
		<bndbox>
			<xmin>14.0</xmin>
			<ymin>82.0</ymin>
			<xmax>99.0</xmax>
			<ymax>167.0</ymax>
		</bndbox>
	</object>
</annotation>