<annotation>
	<folder>VOC1</folder>
	<filename>0_4767.jpg</filename>
	<size>
		<width>256</width>
		<height>256</height>
		<depth>3</depth>
	</size>
	<segmented>0</segmented>
	<object>
		<name>34</name>
		<pose>Unspecified</pose>
		<truncated>0</truncated>
		<difficult>0</difficult>
		<bndbox>
			<xmin>35.0</xmin>
			<ymin>47.0</ymin>
			<xmax>130.0</xmax>
			<ymax>142.0</ymax>
		</bndbox>
	</object>
	<object>
		<name>343</name>
		<pose>Unspecified</pose>
		<truncated>0</truncated>
		<difficult>0</difficult>
		<bndbox>
			<xmin>144.0</xmin>
			<ymin>106.0</ymin>
			<xmax>237.0</xmax>
			<ymax>199.0</ymax>
		</bndbox>
	</object>
	<object>
		<name>991</name>
		<pose>Unspecified</pose>
		<truncated>0</truncated>
		<difficult>0</difficult>
		<bndbox>
			<xmin>4.0</xmin>
			<ymin>151.0</ymin>
			<xmax>94.0</xmax>
			<ymax>241.0</ymax>
		</bndbox>
	</object>
	<object>
		<name>311</name>
		<pose>Unspecified</pose>
		<truncated>0</truncated>
		<difficult>0</difficult>
		<bndbox>
			<xmin>84.0</xmin>
			<ymin>162.0</ymin>
			<xmax>159.0</xmax>
			<ymax>237.0</ymax>
		</bndbox>
	</object>
	<object>
		<name>838</name>
		<pose>Unspecified</pose>
		<truncated>0</truncated>
		<difficult>0</difficult>
		<bndbox>
			<xmin>114.0</xmin>
			<ymin>28.0</ymin>
			<xmax>206.0</xmax>
			<ymax>120.0</ymax>
		</bndbox>
	</object>
</annotation>