<annotation>
	<folder>VOC1</folder>
	<filename>0_5158.jpg</filename>
	<size>
		<width>256</width>
		<height>256</height>
		<depth>3</depth>
	</size>
	<segmented>0</segmented>
	<object>
		<name>820</name>
		<pose>Unspecified</pose>
		<truncated>0</truncated>
		<difficult>0</difficult>
		<bndbox>
			<xmin>46.0</xmin>
			<ymin>40.0</ymin>
			<xmax>121.0</xmax>
			<ymax>115.0</ymax>
		</bndbox>
	</object>
	<object>
		<name>316</name>
		<pose>Unspecified</pose>
		<truncated>0</truncated>
		<difficult>0</difficult>
		<bndbox>
			<xmin>156.0</xmin>
			<ymin>84.0</ymin>
			<xmax>246.0</xmax>
			<ymax>174.0</ymax>
		</bndbox>
	</object>
	<object>
		<name>847</name>
		<pose>Unspecified</pose>
		<truncated>0</truncated>
		<difficult>0</difficult>
		<bndbox>
			<xmin>6.0</xmin>
			<ymin>174.0</ymin>
			<xmax>83.0</xmax>
			<ymax>251.0</ymax>
		</bndbox>
	</object>
	<object>
		<name>432</name>
		<pose>Unspecified</pose>
		<truncated>0</truncated>
		<difficult>0</difficult>
		<bndbox>
			<xmin>84.0</xmin>
			<ymin>122.0</ymin>
			<xmax>178.0</xmax>
			<ymax>216.0</ymax>
		</bndbox>
	</object>
	<object>
		<name>251</name>
		<pose>Unspecified</pose>
		<truncated>0</truncated>
		<difficult>0</difficult>
		<bndbox>
			<xmin>122.0</xmin>
			<ymin>6.0</ymin>
			<xmax>207.0</xmax>
			<ymax>91.0</ymax>
		</bndbox>
	</object>
</annotation>