<annotation>
	<folder>VOC1</folder>
	<filename>0_6352.jpg</filename>
	<size>
		<width>256</width>
		<height>256</height>
		<depth>3</depth>
	</size>
	<segmented>0</segmented>
	<object>
		<name>934</name>
		<pose>Unspecified</pose>
		<truncated>0</truncated>
		<difficult>0</difficult>
		<bndbox>
			<xmin>23.0</xmin>
			<ymin>71.0</ymin>
			<xmax>85.0</xmax>
			<ymax>138.0</ymax>
		</bndbox>
	</object>
	<object>
		<name>741</name>
		<pose>Unspecified</pose>
		<truncated>0</truncated>
		<difficult>0</difficult>
		<bndbox>
			<xmin>115.0</xmin>
			<ymin>70.0</ymin>
			<xmax>186.0</xmax>
			<ymax>146.0</ymax>
		</bndbox>
	</object>
	<object>
		<name>961</name>
		<pose>Unspecified</pose>
		<truncated>0</truncated>
		<difficult>0</difficult>
		<bndbox>
			<xmin>53.0</xmin>
			<ymin>175.0</ymin>
			<xmax>128.0</xmax>
			<ymax>255.0</ymax>
		</bndbox>
	</object>
	<object>
		<name>645</name>
		<pose>Unspecified</pose>
		<truncated>0</truncated>
		<difficult>0</difficult>
		<bndbox>
			<xmin>129.0</xmin>
			<ymin>149.0</ymin>
			<xmax>221.0</xmax>
			<ymax>246.0</ymax>
		</bndbox>
	</object>
</annotation>