<annotation>
	<folder>VOC1</folder>
	<filename>0_7079.jpg</filename>
	<size>
		<width>256</width>
		<height>256</height>
		<depth>3</depth>
	</size>
	<segmented>0</segmented>
	<object>
		<name>322</name>
		<pose>Unspecified</pose>
		<truncated>0</truncated>
		<difficult>0</difficult>
		<bndbox>
			<xmin>27.0</xmin>
			<ymin>18.0</ymin>
			<xmax>105.0</xmax>
			<ymax>96.0</ymax>
		</bndbox>
	</object>
	<object>
		<name>171</name>
		<pose>Unspecified</pose>
		<truncated>0</truncated>
		<difficult>0</difficult>
		<bndbox>
			<xmin>155.0</xmin>
			<ymin>72.0</ymin>
			<xmax>236.0</xmax>
			<ymax>153.0</ymax>
		</bndbox>
	</object>
	<object>
		<name>475</name>
		<pose>Unspecified</pose>
		<truncated>0</truncated>
		<difficult>0</difficult>
		<bndbox>
			<xmin>41.0</xmin>
			<ymin>159.0</ymin>
			<xmax>129.0</xmax>
			<ymax>247.0</ymax>
		</bndbox>
	</object>
	<object>
		<name>192</name>
		<pose>Unspecified</pose>
		<truncated>0</truncated>
		<difficult>0</difficult>
		<bndbox>
			<xmin>123.0</xmin>
			<ymin>153.0</ymin>
			<xmax>206.0</xmax>
			<ymax>236.0</ymax>
		</bndbox>
	</object>
</annotation>