<annotation>
	<folder>VOC1</folder>
	<filename>0_8541.jpg</filename>
	<size>
		<width>256</width>
		<height>256</height>
		<depth>3</depth>
	</size>
	<segmented>0</segmented>
	<object>
		<name>72</name>
		<pose>Unspecified</pose>
		<truncated>0</truncated>
		<difficult>0</difficult>
		<bndbox>
			<xmin>24.0</xmin>
			<ymin>17.0</ymin>
			<xmax>107.0</xmax>
			<ymax>100.0</ymax>
		</bndbox>
	</object>
	<object>
		<name>479</name>
		<pose>Unspecified</pose>
		<truncated>0</truncated>
		<difficult>0</difficult>
		<bndbox>
			<xmin>132.0</xmin>
			<ymin>145.0</ymin>
			<xmax>207.0</xmax>
			<ymax>220.0</ymax>
		</bndbox>
	</object>
	<object>
		<name>675</name>
		<pose>Unspecified</pose>
		<truncated>0</truncated>
		<difficult>0</difficult>
		<bndbox>
			<xmin>105.0</xmin>
			<ymin>43.0</ymin>
			<xmax>183.0</xmax>
			<ymax>121.0</ymax>
		</bndbox>
	</object>
	<object>
		<name>294</name>
		<pose>Unspecified</pose>
		<truncated>0</truncated>
		<difficult>0</difficult>
		<bndbox>
			<xmin>30.0</xmin>
			<ymin>118.0</ymin>
			<xmax>121.0</xmax>
			<ymax>209.0</ymax>
		</bndbox>
	</object>
</annotation>