<annotation>
	<folder>VOC1</folder>
	<filename>0_8681.jpg</filename>
	<size>
		<width>256</width>
		<height>256</height>
		<depth>3</depth>
	</size>
	<segmented>0</segmented>
	<object>
		<name>995</name>
		<pose>Unspecified</pose>
		<truncated>0</truncated>
		<difficult>0</difficult>
		<bndbox>
			<xmin>35.0</xmin>
			<ymin>19.0</ymin>
			<xmax>110.0</xmax>
			<ymax>94.0</ymax>
		</bndbox>
	</object>
	<object>
		<name>874</name>
		<pose>Unspecified</pose>
		<truncated>0</truncated>
		<difficult>0</difficult>
		<bndbox>
			<xmin>162.0</xmin>
			<ymin>67.0</ymin>
			<xmax>250.0</xmax>
			<ymax>155.0</ymax>
		</bndbox>
	</object>
	<object>
		<name>684</name>
		<pose>Unspecified</pose>
		<truncated>0</truncated>
		<difficult>0</difficult>
		<bndbox>
			<xmin>4.0</xmin>
			<ymin>102.0</ymin>
			<xmax>93.0</xmax>
			<ymax>191.0</ymax>
		</bndbox>
	</object>
	<object>
		<name>875</name>
		<pose>Unspecified</pose>
		<truncated>0</truncated>
		<difficult>0</difficult>
		<bndbox>
			<xmin>82.0</xmin>
			<ymin>147.0</ymin>
			<xmax>176.0</xmax>
			<ymax>241.0</ymax>
		</bndbox>
	</object>
	<object>
		<name>297</name>
		<pose>Unspecified</pose>
		<truncated>0</truncated>
		<difficult>0</difficult>
		<bndbox>
			<xmin>161.0</xmin>
			<ymin>159.0</ymin>
			<xmax>250.0</xmax>
			<ymax>248.0</ymax>
		</bndbox>
	</object>
</annotation>